youtubepy/__init__.py
youtubepy/safesearch.txt
youtubepy-6.0.2.dist-info/LICENSE.txt
youtubepy-6.0.2.dist-info/METADATA
youtubepy-6.0.2.dist-info/WHEEL
youtubepy-6.0.2.dist-info/top_level.txt
youtubepy-6.0.2.dist-info/RECORD
