Metadata-Version: 2.1
Name: youtubepy
Version: 6.0.2
Summary: youtubepy is a package to search for youtube videos with python
Home-page: https://github.com/toxicrecker/youtubepy
Author: toxicrecker
Author-email: reck.channel.mainlead@gmail.com
License: UNKNOWN
Platform: UNKNOWN
Classifier: Programming Language :: Python :: 3
Classifier: License :: OSI Approved :: MIT License
Classifier: Operating System :: OS Independent
Requires-Python: >=3.6
